phylogenetic_tree_vis/__init__.py
phylogenetic_tree_vis/generateConstraints.py
phylogenetic_tree_vis/generateSpatialTemporalInfo.py
phylogenetic_tree_vis/generateTreeStructure.py
phylogenetic_tree_vis/generateVis.py
phylogenetic_tree_vis/loadNexus.py
phylogenetic_tree_vis/node.py
phylogenetic_tree_vis/transTree.py
phylogenetic_tree_vis/tree.py
phylogenetic_tree_vis/__pycache__/__init__.cpython-311.pyc
phylogenetic_tree_vis/__pycache__/generateConstraints.cpython-311.pyc
phylogenetic_tree_vis/__pycache__/generateSpatialTemporalInfo.cpython-311.pyc
phylogenetic_tree_vis/__pycache__/generateTreeStructure.cpython-311.pyc
phylogenetic_tree_vis/__pycache__/generateVis.cpython-311.pyc
phylogenetic_tree_vis/__pycache__/loadNexus.cpython-311.pyc
phylogenetic_tree_vis/__pycache__/node.cpython-311.pyc
phylogenetic_tree_vis/__pycache__/transTree.cpython-311.pyc
phylogenetic_tree_vis/__pycache__/tree.cpython-311.pyc
phylogenetic_tree_vis-0.0.1.dist-info/METADATA
phylogenetic_tree_vis-0.0.1.dist-info/WHEEL
phylogenetic_tree_vis-0.0.1.dist-info/top_level.txt
phylogenetic_tree_vis-0.0.1.dist-info/RECORD
