Metadata-Version: 2.1
Name: phylogenetic_tree_vis
Version: 0.0.1
Summary: Project Description
Author: qwerame
Classifier: Framework :: Dash
Requires-Dist: dash >=2.0.0
Requires-Dist: phylogenetic-tree-vis-comp ==0.0.1
